goat/__init__.py
goat/matcher.py
goat/model.py
goat/string.py
goat/types.py
goat-0.3.2.dist-info/DESCRIPTION.rst
goat-0.3.2.dist-info/METADATA
goat-0.3.2.dist-info/RECORD
goat-0.3.2.dist-info/WHEEL
goat-0.3.2.dist-info/metadata.json
goat-0.3.2.dist-info/top_level.txt
